rsa_archer/__init__.py
rsa_archer/archer_instance.py
rsa_archer/record.py
rsa_archer/user.py
rsa_archer/tests/__init__.py
rsa_archer/tests/config.py
rsa_archer/tests/test_archer_instance.py
rsa_archer-0.1.3.dist-info/LICENCE.txt
rsa_archer-0.1.3.dist-info/METADATA
rsa_archer-0.1.3.dist-info/WHEEL
rsa_archer-0.1.3.dist-info/top_level.txt
rsa_archer-0.1.3.dist-info/RECORD
