Metadata-Version: 2.1
Name: rsa-archer
Version: 0.1.3
Summary: RSA Archer REST and GRC API library
Home-page: https://github.com/mwa21/rsa_archer
Author: Aleksei Aikashev
Author-email: a.aykashev@gmail.com
License: UNKNOWN
Keywords: RSA Archer GRC Library
Platform: UNKNOWN
Classifier: Programming Language :: Python :: 3
Classifier: License :: OSI Approved :: MIT License
Classifier: Operating System :: OS Independent
Classifier: Intended Audience :: Developers
Classifier: Topic :: Software Development :: Libraries :: Python Modules
Classifier: Topic :: Software Development :: Libraries
Requires-Dist: requests
